{
  "@microsoft/generator-sharepoint": {
    "plusBeta": false,
    "isCreatingSolution": true,
    "nodeVersion": "18.18.2",
    "sdksVersions": {
      "@microsoft/microsoft-graph-client": "3.0.2",
      "@microsoft/teams-js": "2.12.0"
    },
    "version": "1.18.0",
    "libraryName": "engage-squared-test",
    "libraryId": "2e246acf-1361-47e4-9415-48039f0118e0",
    "environment": "spo",
    "packageManager": "npm",
    "solutionName": "engageSquaredTest",
    "solutionShortDescription": "engageSquaredTest description",
    "skipFeatureDeployment": true,
    "isDomainIsolated": false,
    "componentType": "webpart"
  }
}
